urlreader/__init__.py
urlreader/utils.py
urlreader-0.1.3.dist-info/LICENSE
urlreader-0.1.3.dist-info/METADATA
urlreader-0.1.3.dist-info/WHEEL
urlreader-0.1.3.dist-info/top_level.txt
urlreader-0.1.3.dist-info/RECORD
