Metadata-Version: 2.1
Name: urlreader
Version: 0.1.3
Summary: URLReader: a wrapper around macOS’s NSURLSession, etc. for PyObjC apps
Home-page: https://github.com/verbosus/urlreader
Author: Antonio Cavedoni
Author-email: antonio@cavedoni.org
License: UNKNOWN
Platform: UNKNOWN
Classifier: Programming Language :: Python :: 3
Classifier: License :: OSI Approved :: MIT License
Classifier: Operating System :: MacOS :: MacOS X
Classifier: Development Status :: 3 - Alpha
Classifier: Environment :: MacOS X
Classifier: Environment :: MacOS X :: Cocoa
Classifier: Topic :: Internet
Requires-Python: >=3.6
Requires-Dist: pyobjc (>=5.2)
